[
    {
        "name": "jmadsen",
        "email": "jmadsen@kenect.com",
        "createdAt": "2020-06-25T02:29:23.755Z",
        "updatedAt": "2020-06-25T02:29:23.755Z"
    },
    {
        "name": "Jalisa Quigley",
        "email": "clotilde.corkery@example.com",
        "createdAt": "2020-06-25T02:31:51.233Z",
        "updatedAt": "2020-06-25T02:31:51.233Z"
    },
    {
        "name": "Elijah Wiza",
        "email": "zachery.wunsch@example.com",
        "createdAt": "2020-06-25T02:31:51.240Z",
        "updatedAt": "2020-06-25T02:31:51.240Z"
    },
    {
        "name": "Orval Langosh",
        "email": "rodrick@example.com",
        "createdAt": "2020-06-25T02:31:51.248Z",
        "updatedAt": "2020-06-25T02:31:51.248Z"
    },
    {
        "name": "Harvey King",
        "email": "lyndsay@example.org",
        "createdAt": "2020-06-25T02:31:51.255Z",
        "updatedAt": "2020-06-25T02:31:51.255Z"
    },
    {
        "name": "Mrs. Janice Muller",
        "email": "corie@example.com",
        "createdAt": "2020-06-25T02:31:51.262Z",
        "updatedAt": "2020-06-25T02:31:51.262Z"
    },
    {
        "name": "Ira Stoltenberg",
        "email": "lauryn.langworth@example.org",
        "createdAt": "2020-06-25T02:31:51.269Z",
        "updatedAt": "2020-06-25T02:31:51.269Z"
    },
    {
        "name": "Marcelo Pfeffer",
        "email": "arnette.zieme@example.net",
        "createdAt": "2020-06-25T02:31:51.276Z",
        "updatedAt": "2020-06-25T02:31:51.276Z"
    },
    {
        "name": "Maybell Aufderhar",
        "email": "isiah_johnston@example.org",
        "createdAt": "2020-06-25T02:31:51.282Z",
        "updatedAt": "2020-06-25T02:31:51.282Z"
    },
    {
        "name": "Van Schuppe PhD",
        "email": "rebekah@example.net",
        "createdAt": "2020-06-25T02:31:51.290Z",
        "updatedAt": "2020-06-25T02:31:51.290Z"
    },
    {
        "name": "Suzann Emmerich",
        "email": "sergio@example.org",
        "createdAt": "2020-06-25T02:31:51.299Z",
        "updatedAt": "2020-06-25T02:31:51.299Z"
    },
    {
        "name": "Clemmie Murray IV",
        "email": "onita@example.org",
        "createdAt": "2020-06-25T02:31:51.305Z",
        "updatedAt": "2020-06-25T02:31:51.305Z"
    },
    {
        "name": "Alisha Turcotte",
        "email": "charlotte.lang@example.net",
        "createdAt": "2020-06-25T02:31:51.311Z",
        "updatedAt": "2020-06-25T02:31:51.311Z"
    },
    {
        "name": "Rowena Ritchie",
        "email": "carley@example.com",
        "createdAt": "2020-06-25T02:31:51.318Z",
        "updatedAt": "2020-06-25T02:31:51.318Z"
    },
    {
        "name": "Joel O'Kon",
        "email": "davis@example.net",
        "createdAt": "2020-06-25T02:31:51.327Z",
        "updatedAt": "2020-06-25T02:31:51.327Z"
    },
    {
        "name": "Oswaldo Carroll",
        "email": "annice_dicki@example.com",
        "createdAt": "2020-06-25T02:31:51.333Z",
        "updatedAt": "2020-06-25T02:31:51.333Z"
    },
    {
        "name": "Johnie Langosh",
        "email": "mikel@example.com",
        "createdAt": "2020-06-25T02:31:51.341Z",
        "updatedAt": "2020-06-25T02:31:51.341Z"
    },
    {
        "name": "Louisa Lindgren",
        "email": "phil_kemmer@example.org",
        "createdAt": "2020-06-25T02:31:51.348Z",
        "updatedAt": "2020-06-25T02:31:51.348Z"
    },
    {
        "name": "Marlon Blanda",
        "email": "izola@example.com",
        "createdAt": "2020-06-25T02:31:51.362Z",
        "updatedAt": "2020-06-25T02:31:51.362Z"
    },
    {
        "name": "Tessa O'Keefe",
        "email": "mel@example.org",
        "createdAt": "2020-06-25T02:31:51.368Z",
        "updatedAt": "2020-06-25T02:31:51.368Z"
    },
    {
        "name": "Suzann Wilderman",
        "email": "rodolfo_veum@example.net",
        "createdAt": "2020-06-25T02:31:51.374Z",
        "updatedAt": "2020-06-25T02:31:51.374Z"
    },
    {
        "name": "Ryan H",
        "email": "ryanh@kenect.com",
        "createdAt": "2020-08-10T17:38:55.131Z",
        "updatedAt": "2020-08-10T17:38:55.131Z"
    },
    {
        "name": "J Anderson",
        "email": "janderson@kenect.com",
        "createdAt": "2021-05-03T19:08:42.190Z",
        "updatedAt": "2021-05-03T19:08:42.190Z"
    },
    {
        "name": "Interview Candidate",
        "email": "candidate@example.com",
        "createdAt": "2021-06-16T15:15:56.363Z",
        "updatedAt": "2021-06-16T15:15:56.363Z"
    },
    {
        "name": "Leah M",
        "email": "lmcbeth@kenect.com",
        "createdAt": "2021-06-21T16:35:53.678Z",
        "updatedAt": "2021-06-21T16:35:53.678Z"
    }
]